{
  "annotations": {
    "list": [
      {
        "builtIn": 1,
        "datasource": { "type": "grafana", "uid": "-- Grafana --" },
        "enable": true,
        "hide": true,
        "iconColor": "rgba(0,211,255,1)",
        "name": "Annotations & Alerts",
        "type": "dashboard"
      }
    ]
  },
  "description": "Centralized alert state, SLA uptime tracking, and alert frequency analysis across all teams and servers.",
  "editable": true,
  "fiscalYearStartMonth": 0,
  "graphTooltip": 1,
  "id": null,
  "links": [],
  "refresh": "1m",
  "schemaVersion": 38,
  "tags": ["alerting", "sla", "monitoring"],
  "time": { "from": "now-30d", "to": "now" },
  "timepicker": {},
  "timezone": "browser",
  "title": "Alerts & SLA Tracking",
  "uid": "enterprise-alerts-sla",
  "version": 1,
  "templating": {
    "list": [
      {
        "current": { "text": "Prometheus", "value": "prometheus-uid" },
        "includeAll": false,
        "label": "Data Source",
        "name": "datasource",
        "options": [],
        "query": "prometheus",
        "refresh": 1,
        "type": "datasource"
      },
      {
        "current": { "text": "linux_servers", "value": "linux_servers" },
        "hide": 0,
        "label": "Linux Job",
        "name": "linux_job",
        "options": [{ "selected": true, "text": "linux_servers", "value": "linux_servers" }],
        "query": "linux_servers",
        "type": "textbox"
      },
      {
        "current": { "text": "windows_servers", "value": "windows_servers" },
        "hide": 0,
        "label": "Windows Job",
        "name": "windows_job",
        "options": [{ "selected": true, "text": "windows_servers", "value": "windows_servers" }],
        "query": "windows_servers",
        "type": "textbox"
      },
      {
        "current": { "text": "apache_servers", "value": "apache_servers" },
        "hide": 0,
        "label": "Apache Job",
        "name": "apache_job",
        "options": [{ "selected": true, "text": "apache_servers", "value": "apache_servers" }],
        "query": "apache_servers",
        "type": "textbox"
      },
      {
        "current": { "text": "nginx_servers", "value": "nginx_servers" },
        "hide": 0,
        "label": "Nginx Job",
        "name": "nginx_job",
        "options": [{ "selected": true, "text": "nginx_servers", "value": "nginx_servers" }],
        "query": "nginx_servers",
        "type": "textbox"
      },
      {
        "current": { "text": "nodejs_applications", "value": "nodejs_applications" },
        "hide": 0,
        "label": "Node.js Job",
        "name": "nodejs_job",
        "options": [{ "selected": true, "text": "nodejs_applications", "value": "nodejs_applications" }],
        "query": "nodejs_applications",
        "type": "textbox"
      }
    ]
  },

  "panels": [

    {
      "id": 1,
      "type": "stat",
      "title": "Total Firing Alerts",
      "description": "Number of alerts currently in firing state across all teams",
      "gridPos": { "h": 4, "w": 6, "x": 0, "y": 0 },
      "datasource": { "type": "prometheus", "uid": "prometheus-uid" },
      "options": {
        "colorMode": "background",
        "graphMode": "none",
        "justifyMode": "center",
        "orientation": "auto",
        "reduceOptions": { "calcs": ["lastNotNull"], "fields": "", "values": false },
        "textMode": "auto"
      },
      "fieldConfig": {
        "defaults": {
          "color": { "mode": "thresholds" },
          "thresholds": {
            "mode": "absolute",
            "steps": [
              { "color": "green", "value": null },
              { "color": "red",   "value": 1 }
            ]
          },
          "unit": "short",
          "noValue": "0"
        },
        "overrides": []
      },
      "targets": [
        {
          "datasource": { "type": "prometheus", "uid": "prometheus-uid" },
          "expr": "count(ALERTS{alertstate=\"firing\"}) or vector(0)",
          "instant": true,
          "legendFormat": "Firing",
          "refId": "A"
        }
      ]
    },

    {
      "id": 2,
      "type": "stat",
      "title": "Critical Alerts",
      "description": "Alerts with severity=critical currently firing",
      "gridPos": { "h": 4, "w": 6, "x": 6, "y": 0 },
      "datasource": { "type": "prometheus", "uid": "prometheus-uid" },
      "options": {
        "colorMode": "background",
        "graphMode": "none",
        "justifyMode": "center",
        "orientation": "auto",
        "reduceOptions": { "calcs": ["lastNotNull"], "fields": "", "values": false },
        "textMode": "auto"
      },
      "fieldConfig": {
        "defaults": {
          "color": { "mode": "thresholds" },
          "thresholds": {
            "mode": "absolute",
            "steps": [
              { "color": "green", "value": null },
              { "color": "red",   "value": 1 }
            ]
          },
          "unit": "short",
          "noValue": "0"
        },
        "overrides": []
      },
      "targets": [
        {
          "datasource": { "type": "prometheus", "uid": "prometheus-uid" },
          "expr": "count(ALERTS{alertstate=\"firing\",severity=\"critical\"}) or vector(0)",
          "instant": true,
          "legendFormat": "Critical",
          "refId": "A"
        }
      ]
    },

    {
      "id": 3,
      "type": "stat",
      "title": "Warning Alerts",
      "description": "Alerts with severity=warning currently firing",
      "gridPos": { "h": 4, "w": 6, "x": 12, "y": 0 },
      "datasource": { "type": "prometheus", "uid": "prometheus-uid" },
      "options": {
        "colorMode": "background",
        "graphMode": "none",
        "justifyMode": "center",
        "orientation": "auto",
        "reduceOptions": { "calcs": ["lastNotNull"], "fields": "", "values": false },
        "textMode": "auto"
      },
      "fieldConfig": {
        "defaults": {
          "color": { "mode": "thresholds" },
          "thresholds": {
            "mode": "absolute",
            "steps": [
              { "color": "green",  "value": null },
              { "color": "orange", "value": 1 }
            ]
          },
          "unit": "short",
          "noValue": "0"
        },
        "overrides": []
      },
      "targets": [
        {
          "datasource": { "type": "prometheus", "uid": "prometheus-uid" },
          "expr": "count(ALERTS{alertstate=\"firing\",severity=\"warning\"}) or vector(0)",
          "instant": true,
          "legendFormat": "Warning",
          "refId": "A"
        }
      ]
    },

    {
      "id": 4,
      "type": "stat",
      "title": "Servers Online",
      "description": "Percentage of all monitored servers currently reachable",
      "gridPos": { "h": 4, "w": 6, "x": 18, "y": 0 },
      "datasource": { "type": "prometheus", "uid": "prometheus-uid" },
      "options": {
        "colorMode": "background",
        "graphMode": "none",
        "justifyMode": "center",
        "orientation": "auto",
        "reduceOptions": { "calcs": ["lastNotNull"], "fields": "", "values": false },
        "textMode": "auto"
      },
      "fieldConfig": {
        "defaults": {
          "color": { "mode": "thresholds" },
          "thresholds": {
            "mode": "absolute",
            "steps": [
              { "color": "red",    "value": null },
              { "color": "orange", "value": 80 },
              { "color": "yellow", "value": 95 },
              { "color": "green",  "value": 100 }
            ]
          },
          "unit": "percent",
          "decimals": 1,
          "noValue": "N/A"
        },
        "overrides": []
      },
      "targets": [
        {
          "datasource": { "type": "prometheus", "uid": "prometheus-uid" },
          "expr": "count(up == 1) / count(up) * 100",
          "instant": true,
          "legendFormat": "Online %",
          "refId": "A"
        }
      ]
    },

    {
      "id": 5,
      "type": "alertlist",
      "title": "Current Alert State — All Teams",
      "description": "Live view of all firing, pending and error alerts across every team",
      "gridPos": { "h": 9, "w": 24, "x": 0, "y": 4 },
      "options": {
        "alertInstanceLabelFilter": "",
        "alertName": "",
        "dashboardAlerts": false,
        "groupBy": ["team", "severity"],
        "groupMode": "tags",
        "maxItems": 50,
        "sortOrder": 1,
        "stateFilter": {
          "error":   true,
          "firing":  true,
          "noData":  true,
          "normal":  false,
          "pending": true
        },
        "viewMode": "list"
      },
      "targets": []
    },

    {
      "id": 6,
      "type": "row",
      "title": "Server Uptime SLA (selected time range)",
      "collapsed": false,
      "gridPos": { "h": 1, "w": 24, "x": 0, "y": 13 }
    },

    {
      "id": 7,
      "type": "gauge",
      "title": "Windows Servers",
      "gridPos": { "h": 7, "w": 4, "x": 0, "y": 14 },
      "datasource": { "type": "prometheus", "uid": "prometheus-uid" },
      "options": {
        "minVizHeight": 75,
        "minVizWidth": 75,
        "orientation": "auto",
        "reduceOptions": { "calcs": ["lastNotNull"], "fields": "", "values": false },
        "showThresholdLabels": false,
        "showThresholdMarkers": true
      },
      "fieldConfig": {
        "defaults": {
          "color": { "mode": "thresholds" },
          "max": 100, "min": 90,
          "thresholds": {
            "mode": "absolute",
            "steps": [
              { "color": "red",    "value": null },
              { "color": "orange", "value": 95 },
              { "color": "yellow", "value": 99 },
              { "color": "green",  "value": 99.9 }
            ]
          },
          "unit": "percent",
          "decimals": 2
        },
        "overrides": []
      },
      "targets": [
        {
          "datasource": { "type": "prometheus", "uid": "prometheus-uid" },
          "expr": "avg_over_time(up{job=~\"$windows_job\"}[$__range]) * 100",
          "instant": true,
          "legendFormat": "{{server_name}}",
          "refId": "A"
        }
      ]
    },

    {
      "id": 8,
      "type": "gauge",
      "title": "Linux Servers",
      "gridPos": { "h": 7, "w": 4, "x": 4, "y": 14 },
      "datasource": { "type": "prometheus", "uid": "prometheus-uid" },
      "options": {
        "minVizHeight": 75,
        "minVizWidth": 75,
        "orientation": "auto",
        "reduceOptions": { "calcs": ["lastNotNull"], "fields": "", "values": false },
        "showThresholdLabels": false,
        "showThresholdMarkers": true
      },
      "fieldConfig": {
        "defaults": {
          "color": { "mode": "thresholds" },
          "max": 100, "min": 90,
          "thresholds": {
            "mode": "absolute",
            "steps": [
              { "color": "red",    "value": null },
              { "color": "orange", "value": 95 },
              { "color": "yellow", "value": 99 },
              { "color": "green",  "value": 99.9 }
            ]
          },
          "unit": "percent",
          "decimals": 2
        },
        "overrides": []
      },
      "targets": [
        {
          "datasource": { "type": "prometheus", "uid": "prometheus-uid" },
          "expr": "avg_over_time(up{job=~\"$linux_job\"}[$__range]) * 100",
          "instant": true,
          "legendFormat": "{{server_name}}",
          "refId": "A"
        }
      ]
    },

    {
      "id": 9,
      "type": "gauge",
      "title": "Apache Servers",
      "gridPos": { "h": 7, "w": 4, "x": 8, "y": 14 },
      "datasource": { "type": "prometheus", "uid": "prometheus-uid" },
      "options": {
        "minVizHeight": 75,
        "minVizWidth": 75,
        "orientation": "auto",
        "reduceOptions": { "calcs": ["lastNotNull"], "fields": "", "values": false },
        "showThresholdLabels": false,
        "showThresholdMarkers": true
      },
      "fieldConfig": {
        "defaults": {
          "color": { "mode": "thresholds" },
          "max": 100, "min": 90,
          "thresholds": {
            "mode": "absolute",
            "steps": [
              { "color": "red",    "value": null },
              { "color": "orange", "value": 95 },
              { "color": "yellow", "value": 99 },
              { "color": "green",  "value": 99.9 }
            ]
          },
          "unit": "percent",
          "decimals": 2
        },
        "overrides": []
      },
      "targets": [
        {
          "datasource": { "type": "prometheus", "uid": "prometheus-uid" },
          "expr": "avg_over_time(up{job=~\"$apache_job\"}[$__range]) * 100",
          "instant": true,
          "legendFormat": "{{server_name}}",
          "refId": "A"
        }
      ]
    },

    {
      "id": 10,
      "type": "gauge",
      "title": "Nginx Servers",
      "gridPos": { "h": 7, "w": 4, "x": 12, "y": 14 },
      "datasource": { "type": "prometheus", "uid": "prometheus-uid" },
      "options": {
        "minVizHeight": 75,
        "minVizWidth": 75,
        "orientation": "auto",
        "reduceOptions": { "calcs": ["lastNotNull"], "fields": "", "values": false },
        "showThresholdLabels": false,
        "showThresholdMarkers": true
      },
      "fieldConfig": {
        "defaults": {
          "color": { "mode": "thresholds" },
          "max": 100, "min": 90,
          "thresholds": {
            "mode": "absolute",
            "steps": [
              { "color": "red",    "value": null },
              { "color": "orange", "value": 95 },
              { "color": "yellow", "value": 99 },
              { "color": "green",  "value": 99.9 }
            ]
          },
          "unit": "percent",
          "decimals": 2
        },
        "overrides": []
      },
      "targets": [
        {
          "datasource": { "type": "prometheus", "uid": "prometheus-uid" },
          "expr": "avg_over_time(up{job=~\"$nginx_job\"}[$__range]) * 100",
          "instant": true,
          "legendFormat": "{{server_name}}",
          "refId": "A"
        }
      ]
    },

    {
      "id": 11,
      "type": "gauge",
      "title": "Database Servers",
      "gridPos": { "h": 7, "w": 4, "x": 16, "y": 14 },
      "datasource": { "type": "prometheus", "uid": "prometheus-uid" },
      "options": {
        "minVizHeight": 75,
        "minVizWidth": 75,
        "orientation": "auto",
        "reduceOptions": { "calcs": ["lastNotNull"], "fields": "", "values": false },
        "showThresholdLabels": false,
        "showThresholdMarkers": true
      },
      "fieldConfig": {
        "defaults": {
          "color": { "mode": "thresholds" },
          "max": 100, "min": 90,
          "thresholds": {
            "mode": "absolute",
            "steps": [
              { "color": "red",    "value": null },
              { "color": "orange", "value": 95 },
              { "color": "yellow", "value": 99 },
              { "color": "green",  "value": 99.9 }
            ]
          },
          "unit": "percent",
          "decimals": 2
        },
        "overrides": []
      },
      "targets": [
        {
          "datasource": { "type": "prometheus", "uid": "prometheus-uid" },
          "expr": "avg_over_time(up{job=~\"mysql_servers|mssql_servers|postgres_servers\"}[$__range]) * 100",
          "instant": true,
          "legendFormat": "{{server_name}}",
          "refId": "A"
        }
      ]
    },

    {
      "id": 12,
      "type": "gauge",
      "title": "Node.js Applications",
      "gridPos": { "h": 7, "w": 4, "x": 20, "y": 14 },
      "datasource": { "type": "prometheus", "uid": "prometheus-uid" },
      "options": {
        "minVizHeight": 75,
        "minVizWidth": 75,
        "orientation": "auto",
        "reduceOptions": { "calcs": ["lastNotNull"], "fields": "", "values": false },
        "showThresholdLabels": false,
        "showThresholdMarkers": true
      },
      "fieldConfig": {
        "defaults": {
          "color": { "mode": "thresholds" },
          "max": 100, "min": 90,
          "thresholds": {
            "mode": "absolute",
            "steps": [
              { "color": "red",    "value": null },
              { "color": "orange", "value": 95 },
              { "color": "yellow", "value": 99 },
              { "color": "green",  "value": 99.9 }
            ]
          },
          "unit": "percent",
          "decimals": 2
        },
        "overrides": []
      },
      "targets": [
        {
          "datasource": { "type": "prometheus", "uid": "prometheus-uid" },
          "expr": "avg_over_time(up{job=~\"$nodejs_job\"}[$__range]) * 100",
          "instant": true,
          "legendFormat": "{{server_name}}",
          "refId": "A"
        }
      ]
    },

    {
      "id": 13,
      "type": "row",
      "title": "Alert Analysis",
      "collapsed": false,
      "gridPos": { "h": 1, "w": 24, "x": 0, "y": 21 }
    },

    {
      "id": 14,
      "type": "table",
      "title": "Per-Server Uptime — Live Status",
      "description": "Current up/down status for every monitored target with team and environment labels",
      "gridPos": { "h": 9, "w": 13, "x": 0, "y": 22 },
      "datasource": { "type": "prometheus", "uid": "prometheus-uid" },
      "options": {
        "cellHeight": "sm",
        "footer": { "countRows": false, "fields": "", "reducer": ["sum"], "show": false },
        "showHeader": true,
        "sortBy": [{ "desc": true, "displayName": "Status" }]
      },
      "fieldConfig": {
        "defaults": {
          "color": { "mode": "thresholds" },
          "custom": {
            "align": "left",
            "cellOptions": { "type": "auto" },
            "filterable": true,
            "inspect": false
          },
          "thresholds": {
            "mode": "absolute",
            "steps": [
              { "color": "red",   "value": null },
              { "color": "green", "value": 1 }
            ]
          }
        },
        "overrides": [
          {
            "matcher": { "id": "byName", "options": "Status" },
            "properties": [
              { "id": "custom.cellOptions", "value": { "type": "color-background" } },
              { "id": "mappings", "value": [
                { "options": { "0": { "color": "red",   "index": 0, "text": "DOWN"   } }, "type": "value" },
                { "options": { "1": { "color": "green", "index": 1, "text": "UP"     } }, "type": "value" }
              ]}
            ]
          },
          { "matcher": { "id": "byName", "options": "Time"        }, "properties": [{ "id": "custom.hidden", "value": true }] },
          { "matcher": { "id": "byName", "options": "__name__"    }, "properties": [{ "id": "custom.hidden", "value": true }] },
          { "matcher": { "id": "byName", "options": "job"         }, "properties": [{ "id": "displayName",   "value": "Job"    }] },
          { "matcher": { "id": "byName", "options": "instance"    }, "properties": [{ "id": "displayName",   "value": "Instance" }] },
          { "matcher": { "id": "byName", "options": "server_name" }, "properties": [{ "id": "displayName",   "value": "Server Name" }] },
          { "matcher": { "id": "byName", "options": "team"        }, "properties": [{ "id": "displayName",   "value": "Team"   }] },
          { "matcher": { "id": "byName", "options": "environment" }, "properties": [{ "id": "displayName",   "value": "Env"    }] },
          { "matcher": { "id": "byName", "options": "Value"       }, "properties": [{ "id": "displayName",   "value": "Status" }] }
        ]
      },
      "targets": [
        {
          "datasource": { "type": "prometheus", "uid": "prometheus-uid" },
          "expr": "up",
          "instant": true,
          "legendFormat": "",
          "refId": "A"
        }
      ],
      "transformations": [
        { "id": "labelsToFields", "options": { "valueLabel": "Value" } },
        {
          "id": "organize",
          "options": {
            "renameByName": { "Value": "Status" }
          }
        }
      ]
    },

    {
      "id": 15,
      "type": "barchart",
      "title": "Firing Alert Duration — Currently Firing (seconds)",
      "description": "Time each alert has been continuously firing. Longer bars = older unresolved alerts.",
      "gridPos": { "h": 9, "w": 11, "x": 13, "y": 22 },
      "datasource": { "type": "prometheus", "uid": "prometheus-uid" },
      "options": {
        "barRadius": 0.03,
        "barWidth": 0.7,
        "colorByField": "severity",
        "fillOpacity": 80,
        "gradientMode": "none",
        "groupWidth": 0.7,
        "legend": { "displayMode": "list", "placement": "bottom", "showLegend": true },
        "orientation": "horizontal",
        "showValue": "auto",
        "stacking": "none",
        "tooltip": { "mode": "single", "sort": "none" },
        "xTickLabelRotation": 0,
        "xTickLabelSpacing": 200
      },
      "fieldConfig": {
        "defaults": {
          "color": { "mode": "palette-classic" },
          "custom": { "fillOpacity": 80, "hideFrom": { "legend": false, "tooltip": false, "viz": false }, "lineWidth": 1 },
          "unit": "s"
        },
        "overrides": []
      },
      "targets": [
        {
          "datasource": { "type": "prometheus", "uid": "prometheus-uid" },
          "expr": "sort_desc(time() - ALERTS_FOR_STATE)",
          "instant": true,
          "legendFormat": "{{alertname}} | {{team}}",
          "refId": "A"
        }
      ]
    },

    {
      "id": 16,
      "type": "row",
      "title": "Alert State Timeline",
      "collapsed": false,
      "gridPos": { "h": 1, "w": 24, "x": 0, "y": 31 }
    },

    {
      "id": 17,
      "type": "timeseries",
      "title": "Alert Firing Timeline — All Alerts",
      "description": "Shows when each alert was firing over the selected time range. Each line = one alert rule + instance.",
      "gridPos": { "h": 9, "w": 24, "x": 0, "y": 32 },
      "datasource": { "type": "prometheus", "uid": "prometheus-uid" },
      "options": {
        "legend": { "calcs": [], "displayMode": "table", "placement": "right", "showLegend": true },
        "tooltip": { "mode": "multi", "sort": "desc" }
      },
      "fieldConfig": {
        "defaults": {
          "color": { "mode": "palette-classic" },
          "custom": {
            "axisCenteredZero": false,
            "axisColorMode": "text",
            "axisLabel": "",
            "axisPlacement": "auto",
            "barAlignment": 0,
            "drawStyle": "line",
            "fillOpacity": 20,
            "gradientMode": "none",
            "hideFrom": { "legend": false, "tooltip": false, "viz": false },
            "lineInterpolation": "stepAfter",
            "lineWidth": 2,
            "pointSize": 5,
            "scaleDistribution": { "type": "linear" },
            "showPoints": "auto",
            "spanNulls": false,
            "stacking": { "group": "A", "mode": "none" },
            "thresholdsStyle": { "mode": "off" }
          },
          "mappings": [],
          "max": 1, "min": 0,
          "thresholds": {
            "mode": "absolute",
            "steps": [
              { "color": "green", "value": null },
              { "color": "red",   "value": 1 }
            ]
          }
        },
        "overrides": []
      },
      "targets": [
        {
          "datasource": { "type": "prometheus", "uid": "prometheus-uid" },
          "expr": "ALERTS{alertstate=\"firing\"}",
          "legendFormat": "{{alertname}} | {{team}} | {{severity}}",
          "refId": "A"
        }
      ]
    },

    {
      "id": 18,
      "type": "timeseries",
      "title": "Server Availability Timeline — All Servers",
      "description": "1 = server is UP and reachable, 0 = server is DOWN. Gaps indicate no data from exporter.",
      "gridPos": { "h": 9, "w": 24, "x": 0, "y": 41 },
      "datasource": { "type": "prometheus", "uid": "prometheus-uid" },
      "options": {
        "legend": { "calcs": ["mean", "min"], "displayMode": "table", "placement": "right", "showLegend": true },
        "tooltip": { "mode": "multi", "sort": "desc" }
      },
      "fieldConfig": {
        "defaults": {
          "color": { "mode": "palette-classic" },
          "custom": {
            "axisCenteredZero": false,
            "axisLabel": "",
            "axisPlacement": "auto",
            "barAlignment": 0,
            "drawStyle": "line",
            "fillOpacity": 15,
            "gradientMode": "none",
            "hideFrom": { "legend": false, "tooltip": false, "viz": false },
            "lineInterpolation": "stepAfter",
            "lineWidth": 2,
            "pointSize": 5,
            "scaleDistribution": { "type": "linear" },
            "showPoints": "auto",
            "spanNulls": false,
            "stacking": { "group": "A", "mode": "none" },
            "thresholdsStyle": { "mode": "area" }
          },
          "mappings": [
            { "options": { "0": { "color": "red",   "index": 0, "text": "DOWN" } }, "type": "value" },
            { "options": { "1": { "color": "green", "index": 1, "text": "UP"   } }, "type": "value" }
          ],
          "max": 1, "min": 0,
          "thresholds": {
            "mode": "absolute",
            "steps": [
              { "color": "red",   "value": null },
              { "color": "green", "value": 1 }
            ]
          }
        },
        "overrides": []
      },
      "targets": [
        {
          "datasource": { "type": "prometheus", "uid": "prometheus-uid" },
          "expr": "up",
          "legendFormat": "{{server_name}} ({{team}})",
          "refId": "A"
        }
      ]
    }

  ]
}
